Metadata-Version: 2.1
Name: anyio
Version: 4.6.1
Summary: High level compatibility layer for multiple asynchronous event loop implementations
Author-email: Alex Grönholm <alex.gronholm@nextday.fi>
License: MIT
Project-URL: Documentation, https://anyio.readthedocs.io/en/latest/
Project-URL: Changelog, https://anyio.readthedocs.io/en/stable/versionhistory.html
Project-URL: Source code, https://github.com/agronholm/anyio
Project-URL: Issue tracker, https://github.com/agronholm/anyio/issues
Classifier: Development Status :: 5 - Production/Stable
Classifier: Intended Audience :: Developers
Classifier: License :: OSI Approved :: MIT License
Classifier: Framework :: AnyIO
Classifier: Typing :: Typed
Classifier: Programming Language :: Python
Classifier: Programming Language :: Python :: 3
Classifier: Programming Language :: Python :: 3.9
Classifier: Programming Language :: Python :: 3.10
Classifier: Programming Language :: Python :: 3.11
Classifier: Programming Language :: Python :: 3.12
Classifier: Programming Language :: Python :: 3.13
Requires-Python: >=3.9
License-File: LICENSE
Requires-Dist: exceptiongroup>=1.0.2; python_version < "3.11"
Requires-Dist: idna>=2.8
Requires-Dist: sniffio>=1.1
Requires-Dist: typing_extensions>=4.1; python_version < "3.11"
Provides-Extra: trio
Requires-Dist: trio>=0.26.1; extra == "trio"
Provides-Extra: test
Requires-Dist: anyio[trio]; extra == "test"
Requires-Dist: coverage[toml]>=7; extra == "test"
Requires-Dist: exceptiongroup>=1.2.0; extra == "test"
Requires-Dist: hypothesis>=4.0; extra == "test"
Requires-Dist: psutil>=5.9; extra == "test"
Requires-Dist: pytest>=7.0; extra == "test"
Requires-Dist: pytest-mock>=3.6.1; extra == "test"
Requires-Dist: trustme; extra == "test"
Requires-Dist: truststore>=0.9.1; python_version >= "3.10" and extra == "test"
Requires-Dist: uvloop>=0.21.0b1; (platform_python_implementation == "CPython" and platform_system != "Windows") and extra == "test"
Provides-Extra: doc
Requires-Dist: packaging; extra == "doc"
Requires-Dist: Sphinx~=7.4; extra == "doc"
Requires-Dist: sphinx_rtd_theme; extra == "doc"
Requires-Dist: sphinx-autodoc-typehints>=1.2.0; extra == "doc"
